openapi_wmata/__init__.py
openapi_wmata/api_client.py
openapi_wmata/api_response.py
openapi_wmata/configuration.py
openapi_wmata/exceptions.py
openapi_wmata/py.typed
openapi_wmata/rest.py
openapi_wmata/api/__init__.py
openapi_wmata/api/rail_api.py
openapi_wmata/api/stations_api.py
openapi_wmata/api/trains_api.py
openapi_wmata/models/__init__.py
openapi_wmata/models/line_code.py
openapi_wmata/models/lines_object.py
openapi_wmata/models/lines_object_lines_inner.py
openapi_wmata/models/live_train_positions.py
openapi_wmata/models/live_train_positions_train_positions_inner.py
openapi_wmata/models/n_day_time_object.py
openapi_wmata/models/next_trains.py
openapi_wmata/models/next_trains_trains_inner.py
openapi_wmata/models/standard_routes_object.py
openapi_wmata/models/standard_routes_object_standard_routes_inner.py
openapi_wmata/models/standard_routes_object_standard_routes_inner_track_circuits_inner.py
openapi_wmata/models/station_entrances_object.py
openapi_wmata/models/station_entrances_object_entrances_inner.py
openapi_wmata/models/station_information_object.py
openapi_wmata/models/station_information_object_address.py
openapi_wmata/models/station_list_object.py
openapi_wmata/models/station_paths_object.py
openapi_wmata/models/station_paths_object_path_inner.py
openapi_wmata/models/station_timing_object.py
openapi_wmata/models/station_timing_object_station_times_inner.py
openapi_wmata/models/station_to_station_object.py
openapi_wmata/models/station_to_station_object_station_to_station_infos_inner.py
openapi_wmata/models/station_to_station_object_station_to_station_infos_inner_rail_fare.py
openapi_wmata/models/stations_parking_object.py
openapi_wmata/models/stations_parking_object_stations_parking_inner.py
openapi_wmata/models/stations_parking_object_stations_parking_inner_all_day_parking.py
openapi_wmata/models/stations_parking_object_stations_parking_inner_short_term_parking.py
openapi_wmata/models/track_circuits_object.py
openapi_wmata-1.0.4.dist-info/METADATA
openapi_wmata-1.0.4.dist-info/WHEEL
openapi_wmata-1.0.4.dist-info/top_level.txt
openapi_wmata-1.0.4.dist-info/RECORD
